pdfpug/__init__.py
pdfpug/common/__init__.py
pdfpug/common/basepugelement.py
pdfpug/common/enums.py
pdfpug/common/helpers.py
pdfpug/css/semantic.min.css
pdfpug/css/style.css
pdfpug/css/themes/moodswing.css
pdfpug/layouts/__init__.py
pdfpug/layouts/column.py
pdfpug/layouts/grid.py
pdfpug/layouts/helpers.py
pdfpug/layouts/row.py
pdfpug/modules/__init__.py
pdfpug/modules/cell.py
pdfpug/modules/header.py
pdfpug/modules/image.py
pdfpug/modules/images.py
pdfpug/modules/label.py
pdfpug/modules/linebreak.py
pdfpug/modules/list.py
pdfpug/modules/messagebox.py
pdfpug/modules/metainformation.py
pdfpug/modules/orderedlist.py
pdfpug/modules/pagebreak.py
pdfpug/modules/paragraph.py
pdfpug/modules/progressbar.py
pdfpug/modules/row.py
pdfpug/modules/segment.py
pdfpug/modules/segments.py
pdfpug/modules/statistic.py
pdfpug/modules/table.py
pdfpug/modules/tableofcontents.py
pdfpug/modules/unorderedlist.py
pdfpug-0.5.0.dist-info/LICENSE.md
pdfpug-0.5.0.dist-info/METADATA
pdfpug-0.5.0.dist-info/WHEEL
pdfpug-0.5.0.dist-info/top_level.txt
pdfpug-0.5.0.dist-info/RECORD
