Metadata-Version: 2.1
Name: pdfpug
Version: 0.5.0
Summary: Create PDFs from scratch using simple, easy to use APIs
Home-page: https://gitlab.com/krnekhelesh/pdfpug
Author: Nekhelesh Ramananthan
Author-email: krnekhelesh@gmail.com
License: MIT
Platform: UNKNOWN
Classifier: Development Status :: 3 - Alpha
Classifier: Intended Audience :: Developers
Classifier: License :: OSI Approved :: MIT License
Classifier: Programming Language :: Python :: 3
Classifier: Programming Language :: Python :: 3.6
Classifier: Programming Language :: Python :: 3.7
Classifier: Natural Language :: English
Requires-Python: >3.6.0
Requires-Dist: jinja2
Requires-Dist: weasyprint
Requires-Dist: pypugjs
